wetraffic_sdk/__init__.py
wetraffic_sdk/api_client.py
wetraffic_sdk/constants.py
wetraffic_sdk/exceptions.py
wetraffic_sdk/flow.py
wetraffic_sdk/lights.py
wetraffic_sdk/logging_config.py
wetraffic_sdk/main.py
wetraffic_sdk/real_time_map.py
wetraffic_sdk/utils.py
wetraffic_sdk-1.1.4.dist-info/METADATA
wetraffic_sdk-1.1.4.dist-info/WHEEL
wetraffic_sdk-1.1.4.dist-info/RECORD
