Metadata-Version: 2.3
Name: wetraffic-sdk
Version: 1.1.4
Summary: Wetraffic SDK
License: MIT
Author: Trafficlab
Requires-Python: >=3.9,<4.0
Classifier: License :: OSI Approved :: MIT License
Classifier: Programming Language :: Python :: 3
Classifier: Programming Language :: Python :: 3.9
Classifier: Programming Language :: Python :: 3.10
Classifier: Programming Language :: Python :: 3.11
Classifier: Programming Language :: Python :: 3.12
Classifier: Programming Language :: Python :: 3.13
Requires-Dist: pydantic (>=2.7.4,<3.0.0)
Requires-Dist: python-json-logger (>=3.3.0,<4.0.0)
Requires-Dist: requests (>=2.32.2,<3.0.0)
Project-URL: Documentation, https://trafficlabsrl.github.io/wetraffic-sdk
Project-URL: Repository, https://github.com/trafficlabsrl/wetraffic-sdk
